autotrader/__init__.py
autotrader/autobot.py
autotrader/autoplot.py
autotrader/autotrader.py
autotrader/indicators.py
autotrader/strategy.py
autotrader/utilities.py
autotrader/bin/__init__.py
autotrader/bin/cli.py
autotrader/brokers/__init__.py
autotrader/brokers/broker.py
autotrader/brokers/ccxt.py
autotrader/brokers/ib.py
autotrader/brokers/oanda.py
autotrader/brokers/trading.py
autotrader/brokers/virtual.py
autotrader/brokers/yahoo.py
autotrader/comms/__init__.py
autotrader/comms/notifier.py
autotrader/comms/tg.py
autotrader/package_data/__init__.py
autotrader/package_data/autoscale.js
autotrader/package_data/keys.yaml
autotrader-1.1.2.dist-info/LICENSE
autotrader-1.1.2.dist-info/METADATA
autotrader-1.1.2.dist-info/WHEEL
autotrader-1.1.2.dist-info/entry_points.txt
autotrader-1.1.2.dist-info/top_level.txt
autotrader-1.1.2.dist-info/RECORD
