Metadata-Version: 2.1
Name: autotrader
Version: 1.1.2
Summary: A Python-based platform for developing, optimising and deploying automated trading systems.
Home-page: https://kieran-mackle.github.io/AutoTrader/
Author: Kieran Mackle
Author-email: kemackle98@gmail.com
License: gpl-3.0
Project-URL: Bug Tracker, https://github.com/kieran-mackle/AutoTrader/issues
Project-URL: Source Code, https://github.com/kieran-mackle/AutoTrader
Project-URL: Documentation, https://autotrader.readthedocs.io/en/latest/
Keywords: algotrading,finance,crypto,forex,python
Classifier: Programming Language :: Python :: 3.11
Classifier: License :: OSI Approved :: GNU General Public License v3 (GPLv3)
Classifier: Operating System :: OS Independent
Requires-Python: >=3.11
License-File: LICENSE
Requires-Dist: numpy >=1.20.3
Requires-Dist: pandas >=1.3.4
Requires-Dist: art >=5.7
Requires-Dist: PyYAML
Requires-Dist: bokeh ==3.3.0
Requires-Dist: scipy >=1.7.1
Requires-Dist: finta >=1.3
Requires-Dist: tqdm >=4.64.0
Requires-Dist: importlib-resources
Requires-Dist: click >=8.1.3
Requires-Dist: requests >=2.28.1
Requires-Dist: python-telegram-bot >=13.14
Requires-Dist: psutil >=5.9.2
Requires-Dist: prometheus-client >=0.15.0
Provides-Extra: all
Requires-Dist: ccxt >=2.0.53 ; extra == 'all'
Requires-Dist: ccxt-download ; extra == 'all'
Requires-Dist: v20 >=3.0.25.0 ; extra == 'all'
Requires-Dist: ib-insync >=0.9.70 ; extra == 'all'
Requires-Dist: yfinance >=0.1.67 ; extra == 'all'
Requires-Dist: pytest >=7.1.1 ; extra == 'all'
Requires-Dist: black >=22.10.0 ; extra == 'all'
Requires-Dist: sphinx-copybutton >=0.5.0 ; extra == 'all'
Requires-Dist: sphinx-inline-tabs >=2022.1.2b11 ; extra == 'all'
Requires-Dist: myst-parser >=0.18.1 ; extra == 'all'
Requires-Dist: furo >=2022.9.29 ; extra == 'all'
Requires-Dist: sphinx-autobuild >=2021.3.14 ; extra == 'all'
Requires-Dist: commitizen >=2.35.0 ; extra == 'all'
Provides-Extra: ccxt
Requires-Dist: ccxt >=2.0.53 ; extra == 'ccxt'
Requires-Dist: ccxt-download ; extra == 'ccxt'
Provides-Extra: dev
Requires-Dist: pytest >=7.1.1 ; extra == 'dev'
Requires-Dist: black >=22.10.0 ; extra == 'dev'
Requires-Dist: sphinx-copybutton >=0.5.0 ; extra == 'dev'
Requires-Dist: sphinx-inline-tabs >=2022.1.2b11 ; extra == 'dev'
Requires-Dist: myst-parser >=0.18.1 ; extra == 'dev'
Requires-Dist: furo >=2022.9.29 ; extra == 'dev'
Requires-Dist: sphinx-autobuild >=2021.3.14 ; extra == 'dev'
Requires-Dist: commitizen >=2.35.0 ; extra == 'dev'
Provides-Extra: dydx
Requires-Dist: dydx-v3-python >=1.9.0 ; extra == 'dydx'
Provides-Extra: ib
Requires-Dist: ib-insync >=0.9.70 ; extra == 'ib'
Provides-Extra: oanda
Requires-Dist: v20 >=3.0.25.0 ; extra == 'oanda'
Provides-Extra: yfinance
Requires-Dist: yfinance >=0.1.67 ; extra == 'yfinance'
